autoschematics/__init__.py
autoschematics/automodel.py
autoschematics/automodel_test.py
sphinx_autoschematics-0.2.0.dist-info/LICENSE.txt
sphinx_autoschematics-0.2.0.dist-info/METADATA
sphinx_autoschematics-0.2.0.dist-info/WHEEL
sphinx_autoschematics-0.2.0.dist-info/top_level.txt
sphinx_autoschematics-0.2.0.dist-info/RECORD
