Metadata-Version: 2.1
Name: sphinx-autoschematics
Version: 0.2.0
Summary: sphinx-autoschematics provides sphinx extensions for documenting schematics models
Home-page: https://github.com/NerdWalletOSS/sphinx-autoschematics
Author: Evan Borgstrom
Author-email: evan@borgstrom.ca
License: Apache License Version 2.0
Platform: UNKNOWN
Classifier: Development Status :: 4 - Beta
Classifier: Programming Language :: Python :: 3.6
Classifier: Programming Language :: Python :: 3.7
Classifier: Programming Language :: Python :: 3.8
Classifier: Programming Language :: Python :: 3.9
Classifier: Intended Audience :: Developers
Classifier: License :: OSI Approved :: Apache Software License
Classifier: Natural Language :: English
Classifier: Programming Language :: Python
Classifier: Topic :: Software Development :: Libraries
Requires-Python: >=3.6, <4
License-File: LICENSE.txt
Requires-Dist: six
Requires-Dist: schematics (<3,>=2)
Requires-Dist: sphinx
Provides-Extra: test
Requires-Dist: pytest ; extra == 'test'
Requires-Dist: pytest-mock ; extra == 'test'
